LICENSE
README.md
setup.py
dockerx.egg-info/PKG-INFO
dockerx.egg-info/SOURCES.txt
dockerx.egg-info/dependency_links.txt
dockerx.egg-info/requires.txt
dockerx.egg-info/top_level.txt
src/__init__.py
src/dl.py
src/run.py