Metadata-Version: 2.1
Name: dockerx
Version: 0.6.0
Summary: Launcher of Docker containers.
Home-page: https://github.com/luiscarlosgph/docker-with-graphics
Author: Luis C. Garcia-Peraza Herrera
Author-email: luiscarlos.gph@gmail.com
License: MIT
Platform: UNKNOWN
License-File: LICENSE
